{
  "clips": [
    {
      "path": "/home/user/shorts-factory/assets/b-roll/city/sample_city.mp4",
      "duration": 10.0,
      "themes": [
        "city",
        "도시"
      ],
      "source": "local",
      "resolution": ""
    },
    {
      "path": "/home/user/shorts-factory/assets/b-roll/nature/sample_nature.mp4",
      "duration": 10.0,
      "themes": [
        "nature",
        "자연",
        "마음"
      ],
      "source": "local",
      "resolution": ""
    },
    {
      "path": "/home/user/shorts-factory/assets/b-roll/abstract/sample_abstract.mp4",
      "duration": 10.0,
      "themes": [
        "추상",
        "abstract"
      ],
      "source": "local",
      "resolution": ""
    }
  ],
  "total_count": 3,
  "themes": [
    "city",
    "자연",
    "추상",
    "abstract",
    "마음",
    "nature",
    "도시"
  ]
}